cmdkit/__init__.py
cmdkit/ansi.py
cmdkit/app.py
cmdkit/cli.py
cmdkit/config.py
cmdkit/contrib/__init__.py
cmdkit/contrib/builder.py
cmdkit/logging.py
cmdkit/namespace.py
cmdkit/platform.py
cmdkit/py.typed
cmdkit-2.7.6.dist-info/LICENSE
cmdkit-2.7.6.dist-info/METADATA
cmdkit-2.7.6.dist-info/WHEEL
cmdkit-2.7.6.dist-info/RECORD
