Metadata-Version: 2.1
Name: cmdkit
Version: 2.7.6
Summary: A command-line utility toolkit for Python.
Home-page: https://cmdkit.readthedocs.io
License: Apache-2.0
Keywords: command-line,utility,toolkit
Author: Geoffrey Lentner
Author-email: glentner@purdue.edu
Requires-Python: >=3.10,<4.0
Classifier: Development Status :: 5 - Production/Stable
Classifier: License :: OSI Approved :: Apache Software License
Classifier: Programming Language :: Python :: 3
Classifier: Programming Language :: Python :: 3.10
Classifier: Programming Language :: Python :: 3.11
Classifier: Programming Language :: Python :: 3.12
Classifier: Programming Language :: Python :: 3.13
Classifier: Topic :: Software Development :: Libraries :: Application Frameworks
Provides-Extra: toml
Provides-Extra: yaml
Requires-Dist: pyyaml (>=6.0.1,<7.0.0) ; extra == "yaml"
Requires-Dist: tomli (>=2.1.0,<3.0.0) ; extra == "toml"
Requires-Dist: tomli-w (>=1.1.0,<2.0.0) ; extra == "toml"
Project-URL: Documentation, https://cmdkit.readthedocs.io
Project-URL: Repository, https://github.com/glentner/cmdkit
